funcbox/__init__.py
funcbox/dijkstra.py
funcbox/misc.py
funcbox/sieve_of_eratosthenes.py
funcbox-0.3.1.dist-info/licenses/LICENSE
funcbox-0.3.1.dist-info/METADATA
funcbox-0.3.1.dist-info/WHEEL
funcbox-0.3.1.dist-info/top_level.txt
funcbox-0.3.1.dist-info/RECORD
