Metadata-Version: 2.4
Name: funcbox
Version: 0.3.1
Summary: A functional utility box with various functions
Home-page: https://github.com/adityaprasad502/funcbox
Author: Aditya Prasad S
Author-email: plutoniumx502@gmail.com
Classifier: Programming Language :: Python :: 3
Classifier: License :: OSI Approved :: MIT License
Classifier: Operating System :: OS Independent
Requires-Python: >=3.6
License-File: LICENSE
Dynamic: author
Dynamic: author-email
Dynamic: classifier
Dynamic: description
Dynamic: description-content-type
Dynamic: home-page
Dynamic: license-file
Dynamic: requires-python
Dynamic: summary
